[
    {
        "type": "Entry",
        "position": [
            165,
            42
        ],
        "size": [
            100,
            20
        ],
        "current_value": "",
        "values": []
    },
    {
        "type": "Entry",
        "position": [
            44,
            81
        ],
        "size": [
            419,
            249
        ],
        "current_value": "",
        "values": []
    },
    {
        "type": "Combobox",
        "position": [
            288,
            44
        ],
        "size": [
            100,
            20
        ],
        "current_value": "",
        "values": [
            "Option 1",
            "Option 2",
            "Option 3"
        ]
    },
    {
        "type": "Combobox",
        "position": [
            249,
            349
        ],
        "size": [
            100,
            20
        ],
        "current_value": "",
        "values": [
            "Option 1",
            "Option 2",
            "Option 3"
        ]
    },
    {
        "type": "Label",
        "position": [
            45,
            40
        ],
        "size": [
            100,
            20
        ],
        "current_value": "Label",
        "values": []
    },
    {
        "type": "Button",
        "position": [
            368,
            352
        ],
        "size": [
            100,
            20
        ],
        "current_value": "Button",
        "values": []
    }
]